mahabharata/__init__.py
mahabharata/__main__.py
mahabharata/models/__init__.py
mahabharata/models/poem.py
mahabharata/services/__init__.py
mahabharata/services/cli_service/__init__.py
mahabharata/services/cli_service/_commands.py
mahabharata/services/cli_service/group.py
mahabharata/services/poet_service/__init__.py
mahabharata/services/poet_service/query.py
mahabharata-0.2.0.dist-info/WHEEL
mahabharata-0.2.0.dist-info/METADATA
mahabharata-0.2.0.dist-info/RECORD
