Metadata-Version: 2.1
Name: mahabharata
Version: 0.2.0
Summary: 
Author: Sharlon Regales
Author-email: sharlon.regales@tno.nl
Requires-Python: >=3.7,<4.0
Classifier: Programming Language :: Python :: 3
Classifier: Programming Language :: Python :: 3.7
Classifier: Programming Language :: Python :: 3.8
Classifier: Programming Language :: Python :: 3.9
Provides-Extra: api
Requires-Dist: click (>=8.0.1,<9.0.0)
Requires-Dist: fastapi (>=0.68.0,<0.69.0); extra == "api"
Requires-Dist: gunicorn (>=20.1.0,<21.0.0); extra == "api"
Requires-Dist: pydantic (>=1.8.2,<2.0.0); python_version >= "3.7" and python_version < "4.0"
Requires-Dist: uvicorn (>=0.15.0,<0.16.0); extra == "api"
